.installed.cfg
CHANGES.txt
CREDITS.txt
MANIFEST.in
README.txt
bootstrap.py
buildout.cfg
setup.py
src/hurry/__init__.py
src/hurry.slimbox.egg-info/PKG-INFO
src/hurry.slimbox.egg-info/SOURCES.txt
src/hurry.slimbox.egg-info/dependency_links.txt
src/hurry.slimbox.egg-info/entry_points.txt
src/hurry.slimbox.egg-info/namespace_packages.txt
src/hurry.slimbox.egg-info/not-zip-safe
src/hurry.slimbox.egg-info/requires.txt
src/hurry.slimbox.egg-info/top_level.txt
src/hurry/slimbox/__init__.py
src/hurry/slimbox/configure.zcml
src/hurry/slimbox/prepare.py
src/hurry/slimbox/slimbox.txt
src/hurry/slimbox/tests.py
src/hurry/slimbox/slimbox-build/README.txt
src/hurry/slimbox/slimbox-build/example.html
src/hurry/slimbox/slimbox-build/example.jpg
src/hurry/slimbox/slimbox-build/css/closelabel.gif
src/hurry/slimbox/slimbox-build/css/loading.gif
src/hurry/slimbox/slimbox-build/css/nextlabel.gif
src/hurry/slimbox/slimbox-build/css/prevlabel.gif
src/hurry/slimbox/slimbox-build/css/slimbox2.css
src/hurry/slimbox/slimbox-build/extra/autoactivation.js
src/hurry/slimbox/slimbox-build/extra/flickr.js
src/hurry/slimbox/slimbox-build/extra/picasaweb.js
src/hurry/slimbox/slimbox-build/js/slimbox2.js
src/hurry/slimbox/slimbox-build/src/autoload.js
src/hurry/slimbox/slimbox-build/src/slimbox2.js