Metadata-Version: 1.0
Name: hurry.slimbox
Version: 2.03
Summary: hurry.resource style resources for Slimbox.
Home-page: UNKNOWN
Author: Souheil Chelfouh
Author-email: trollfot@gmail.com
License: ZPL 2.1
Keywords: jQuery Slimbox Zope3 Popup
Platform: UNKNOWN
